<?xml version="1.0" encoding="UTF-8"?>
<feature
      id="de.tools400.rpgunit.spooledfileviewer"
      label="iRPGUnit Spooled File Viewer Feature (recommended, if iSphere is missing)"
      version="5.1.0.b006"
      provider-name="Tools400"
      plugin="de.tools400.rpgunit.core">

   <description url="https://tools-400.github.io/irpgunit/">
      %description
   </description>

   <copyright url="https://tools-400.github.io/irpgunit/">
      %copyright
   </copyright>

   <license url="http://www.gnu.org/licenses/gpl-3.0.html">
      %license
   </license>

   <url>
      <update label="iRPGUnit - Remote Update Site" url="https://tools-400.github.io/irpgunit/update-site/eclipse/rdi8.0/"/>
      <discovery label="iRPGUnit Project Team" url="http://www.tools400.de"/>
   </url>

   <requires>
      <import feature="de.tools400.rpgunit.core" version="5.1.0.b006" match="greaterOrEqual"/>
   </requires>

   <plugin
         id="de.tools400.rpgunit.spooledfileviewer"
         download-size="0"
         install-size="0"
         version="0.0.0"
         unpack="false"/>

</feature>
